README.rst
requirements.txt
setup.py
shire/__init__.py
shire/cli.py
shire/config.py
shire/const.py
shire/exceptions.py
shire/hostler.py
shire/job.py
shire/logger.py
shire/manager.py
shire/models.py
shire/pool.py
shire/pool_starter.py
shire/redis_managers.py
shire/scheduler.py
shire/scribe.py
shire/utils.py
shire/whip.py
shire/workhorse.py
shire.egg-info/PKG-INFO
shire.egg-info/SOURCES.txt
shire.egg-info/dependency_links.txt
shire.egg-info/entry_points.txt
shire.egg-info/requires.txt
shire.egg-info/top_level.txt