Metadata-Version: 1.1
Name: shire
Version: 0.1.5.dev0
Summary: Heavy-job queue processor
Home-page: https://bitbucket.org/suguby/shire
Author: Suguby
Author-email: suguby@gmail.com
License: MIT
Keywords: queue job task shire
Platform: UNKNOWN
Classifier: Development Status :: 3 - Alpha
Classifier: Intended Audience :: Developers
Classifier: License :: OSI Approved :: MIT License
Classifier: Natural Language :: English
Classifier: Natural Language :: Russian
Classifier: Programming Language :: Python :: 2.7
Classifier: Programming Language :: Python :: 3.5
Classifier: Programming Language :: Python :: 3.6
